{
    "fluentMethods": true,
    "clientRootFolder": "",
    "relationships": [],
    "fields": [
        {
            "fieldName": "name",
            "fieldType": "String",
            "fieldValidateRules": [
                "required",
                "unique",
                "maxlength"
            ],
            "fieldValidateRulesMaxlength": "40"
        },
        {
            "fieldName": "description",
            "fieldType": "String"
        },
        {
            "fieldName": "version",
            "fieldType": "String",
            "fieldValidateRules": [
                "required"
            ]
        },
        {
            "fieldName": "enabled",
            "fieldType": "Boolean"
        }
    ],
    "changelogDate": "20190905075139",
    "dto": "no",
    "searchEngine": false,
    "service": "serviceImpl",
    "entityTableName": "workflow",
    "databaseType": "sql",
    "jpaMetamodelFiltering": false,
    "pagination": "pagination"
}
